nonebot_plugin_BiliRequestAll/__init__.py
nonebot_plugin_BiliRequestAll/config.py
nonebot_plugin_BiliRequestAll/controller/__init__.py
nonebot_plugin_BiliRequestAll/controller/api.py
nonebot_plugin_BiliRequestAll/controller/r_info.py
nonebot_plugin_BiliRequestAll/controller/r_request.py
nonebot_plugin_BiliRequestAll/controller/r_setting.py
nonebot_plugin_BiliRequestAll/utils/__init__.py
nonebot_plugin_BiliRequestAll/utils/f_config.py
nonebot_plugin_bilirequestall-0.3.4.dist-info/LICENSE
nonebot_plugin_bilirequestall-0.3.4.dist-info/METADATA
nonebot_plugin_bilirequestall-0.3.4.dist-info/WHEEL
nonebot_plugin_bilirequestall-0.3.4.dist-info/RECORD
