Metadata-Version: 2.1
Name: nonebot-plugin-BiliRequestAll
Version: 0.3.4
Summary: 以B站UID审核入群 😎
License: MIT
Author: Shadow403
Author-email: admin@shadow403.cn
Requires-Python: >=3.10.0
Classifier: License :: OSI Approved :: MIT License
Classifier: Programming Language :: Python :: 3
Classifier: Programming Language :: Python :: 3.10
Classifier: Programming Language :: Python :: 3.11
Classifier: Programming Language :: Python :: 3.12
Classifier: Programming Language :: Python :: 3.13
Requires-Dist: httpx (>=0.27.0)
Requires-Dist: nonebot-adapter-onebot (>=2.4.0)
Requires-Dist: nonebot2 (>=2.2.0)
